Aemulator/__init__.py
Aemulator/aemulator.py
Aemulator-0.1.dist-info/DESCRIPTION.rst
Aemulator-0.1.dist-info/METADATA
Aemulator-0.1.dist-info/RECORD
Aemulator-0.1.dist-info/WHEEL
Aemulator-0.1.dist-info/metadata.json
Aemulator-0.1.dist-info/top_level.txt
