Metadata-Version: 2.0
Name: Aemulator
Version: 0.1
Summary: Abstract base class for Aemulus Project emulators.
Home-page: https://github.com/AemulusProject/Aemulator
Author: Sean McLaughlin
Author-email: swmclau2@stanford.edu
License: UNKNOWN
Platform: UNKNOWN
